// class version 50.0 (50)
// access flags 0x1
public class TileMultipart_cmp$$1 extends codechicken/multipart/TileMultipart  implements codechicken/multipart/TileMultipartClient  {


  // access flags 0x1
  public <init>()V
    ALOAD 0
    INVOKESPECIAL codechicken/multipart/TileMultipart.<init> ()V
    ALOAD 0
    INVOKESTATIC codechicken/multipart/TileMultipartClient$class.$init$ (Lcodechicken/multipart/TileMultipartClient;)V
    RETURN
    MAXSTACK = 1
    MAXLOCALS = 1

  // access flags 0x1
  public renderStatic(Lcodechicken/lib/vec/Vector3;I)Z
    ALOAD 0
    ALOAD 1
    ILOAD 2
    INVOKESTATIC codechicken/multipart/TileMultipartClient$class.renderStatic (Lcodechicken/multipart/TileMultipartClient;Lcodechicken/lib/vec/Vector3;I)Z
    IRETURN
    MAXSTACK = 3
    MAXLOCALS = 3

  // access flags 0x1
  public renderDynamic(Lcodechicken/lib/vec/Vector3;FI)V
    ALOAD 0
    ALOAD 1
    FLOAD 2
    ILOAD 3
    INVOKESTATIC codechicken/multipart/TileMultipartClient$class.renderDynamic (Lcodechicken/multipart/TileMultipartClient;Lcodechicken/lib/vec/Vector3;FI)V
    RETURN
    MAXSTACK = 4
    MAXLOCALS = 4

  // access flags 0x1
  public randomDisplayTick(Ljava/util/Random;)V
    ALOAD 0
    ALOAD 1
    INVOKESTATIC codechicken/multipart/TileMultipartClient$class.randomDisplayTick (Lcodechicken/multipart/TileMultipartClient;Ljava/util/Random;)V
    RETURN
    MAXSTACK = 2
    MAXLOCALS = 2

  // access flags 0x1
  public shouldRenderInPass(I)Z
    ALOAD 0
    ILOAD 1
    INVOKESTATIC codechicken/multipart/TileMultipartClient$class.shouldRenderInPass (Lcodechicken/multipart/TileMultipartClient;I)Z
    IRETURN
    MAXSTACK = 2
    MAXLOCALS = 2

  // access flags 0x1
  public getRenderBoundingBox()Lnet/minecraft/util/AxisAlignedBB;
    ALOAD 0
    INVOKESTATIC codechicken/multipart/TileMultipartClient$class.getRenderBoundingBox (Lcodechicken/multipart/TileMultipartClient;)Lnet/minecraft/util/AxisAlignedBB;
    ARETURN
    MAXSTACK = 1
    MAXLOCALS = 1
}
